mcp_server_diff_python/__init__.py
mcp_server_diff_python/server.py
mcp_server_diff_python-0.1.2.dist-info/METADATA
mcp_server_diff_python-0.1.2.dist-info/WHEEL
mcp_server_diff_python-0.1.2.dist-info/entry_points.txt
mcp_server_diff_python-0.1.2.dist-info/RECORD
